example/__init__.py
example/run_long_running_task.py
example/run_task.py
example/tasks.py
huey_worker/__init__.py
huey_worker/settings.py
huey_worker/urls.py
huey_worker/wsgi.py
hueyx/__init__.py
hueyx/consumer.py
hueyx/queues.py
hueyx/redis_huey.py
hueyx/settings_reader.py
hueyx/management/__init__.py
hueyx/management/commands/__init__.py
hueyx/management/commands/run_hueyx.py
hueyx/models/__init__.py
hueyx/tests/__init__.py
hueyx/tests/test_heartbeat.py
hueyx/tests/test_queues.py
hueyx/tests/test_settings_reader.py
hueyx-1.0.3.dist-info/LICENSE
hueyx-1.0.3.dist-info/METADATA
hueyx-1.0.3.dist-info/WHEEL
hueyx-1.0.3.dist-info/top_level.txt
hueyx-1.0.3.dist-info/RECORD
