Metadata-Version: 2.1
Name: hueyx
Version: 1.0.3
Summary: Django huey extension which supports multiple huey queues.
Home-page: https://github.com/APGSGA/hueyx
Author: Severin Bühler
Author-email: severin.buehler@apgsga.ch
License: MIT License
Platform: UNKNOWN
Classifier: Environment :: Web Environment
Classifier: Framework :: Django
Classifier: Framework :: Django :: 2.2
Classifier: Framework :: Django :: 3.0
Classifier: Framework :: Django :: 3.1
Classifier: Framework :: Django :: 3.2
Classifier: Intended Audience :: Developers
Classifier: License :: OSI Approved :: MIT License
Classifier: Operating System :: OS Independent
Classifier: Programming Language :: Python :: 3
Classifier: Programming Language :: Python :: 3.6
Classifier: Programming Language :: Python :: 3.7
Classifier: Programming Language :: Python :: 3.8
Classifier: Programming Language :: Python :: 3.9
Classifier: Topic :: Internet :: WWW/HTTP
Classifier: Topic :: Internet :: WWW/HTTP :: Dynamic Content
Requires-Dist: cached-property
Requires-Dist: huey (>=2.3.0)
Requires-Dist: python-redis-lock
Requires-Dist: redis
